blender_renderer/__init__.py
blender_renderer/cleaner.py
blender_renderer/renderer.py
blender_renderer/scripts/get_render_settings.py
blender_renderer/scripts/get_texture_names.py
blender_renderer/scripts/render.py
blender_renderer/scripts/unpack.py
Blender_Renderer-1.2.1.dist-info/LICENSE
Blender_Renderer-1.2.1.dist-info/METADATA
Blender_Renderer-1.2.1.dist-info/WHEEL
Blender_Renderer-1.2.1.dist-info/top_level.txt
Blender_Renderer-1.2.1.dist-info/RECORD
