Metadata-Version: 2.1
Name: Blender-Renderer
Version: 1.2.1
Summary: Render blender scenes
Home-page: https://github.com/skillor/blender-render-api
Author: skillor
Author-email: skillor@gmx.net
License: MIT
Keywords: blender,render,api
Classifier: Programming Language :: Python :: 3 :: Only
Classifier: Topic :: Multimedia :: Graphics
Requires-Python: >=3
License-File: LICENSE
